{"cameraMode":{"drawMode":0,"name":"Shaded","section":"Shading Mode"},"sceneLighting":true,"audioPlay":false,"sceneViewState":{"m_AlwaysRefresh":false,"showFog":true,"showSkybox":true,"showFlares":true,"showImageEffects":true,"showParticleSystems":true,"showVisualEffectGraphs":true,"m_FxEnabled":true},"in2DMode":false,"pivot":{"x":146.52310180664063,"y":-89.65290832519531,"z":-342.5882873535156},"rotation":{"x":0.37214115262031557,"y":-0.591205894947052,"z":0.3537004888057709,"w":0.6221483945846558},"size":80.85357666015625,"orthographic":false}